LICENSE
README.md
setup.py
cnmaptiling/__init__.py
cnmaptiling/angle.py
cnmaptiling/newstandard.py
cnmaptiling/oldstandard.py
cnmaptiling/scale.py
cnmaptiling.egg-info/PKG-INFO
cnmaptiling.egg-info/SOURCES.txt
cnmaptiling.egg-info/dependency_links.txt
cnmaptiling.egg-info/top_level.txt