Metadata-Version: 2.2
Name: cnmaptiling
Version: 0.1.0
Summary: A Python library for tiling based on Chinese mapping standards.
Home-page: https://github.com/k96e/cnmaptiling
Author: k96e
Author-email: zy1835562526@gmail.com
License: MIT
Classifier: Programming Language :: Python :: 3
Classifier: Programming Language :: Python :: 3.10
Classifier: License :: OSI Approved :: MIT License
Classifier: Operating System :: OS Independent
Classifier: Intended Audience :: Developers
Classifier: Topic :: Scientific/Engineering :: GIS
Requires-Python: >=3.6
License-File: LICENSE
Dynamic: author
Dynamic: author-email
Dynamic: classifier
Dynamic: description
Dynamic: description-content-type
Dynamic: home-page
Dynamic: license
Dynamic: requires-python
Dynamic: summary
